torrent_downloader_gui.py
torrent_downloader/__init__.py
torrent_downloader_python-1.1.11.dist-info/METADATA
torrent_downloader_python-1.1.11.dist-info/WHEEL
torrent_downloader_python-1.1.11.dist-info/entry_points.txt
torrent_downloader_python-1.1.11.dist-info/top_level.txt
torrent_downloader_python-1.1.11.dist-info/RECORD
