Metadata-Version: 2.4
Name: torrent-downloader-python
Version: 1.1.11
Summary: A Torrent Downloader with a graphical user interface built using Tkinter and libtorrent
Home-page: https://github.com/stevenbtc/torrent-downloader
Author: Steven Yan
Author-email: yulong.yan@uqconnect.edu.au
Classifier: Development Status :: 4 - Beta
Classifier: Intended Audience :: End Users/Desktop
Classifier: License :: OSI Approved :: MIT License
Classifier: Programming Language :: Python :: 3
Classifier: Programming Language :: Python :: 3.8
Classifier: Programming Language :: Python :: 3.9
Classifier: Programming Language :: Python :: 3.10
Classifier: Programming Language :: Python :: 3.11
Classifier: Programming Language :: Python :: 3.12
Classifier: Operating System :: OS Independent
Classifier: Topic :: Internet :: File Transfer Protocol (FTP)
Requires-Python: >=3.8
Requires-Dist: libtorrent>=2.0.0
Dynamic: author
Dynamic: author-email
Dynamic: classifier
Dynamic: description
Dynamic: description-content-type
Dynamic: home-page
Dynamic: requires-dist
Dynamic: requires-python
Dynamic: summary
